tty_egpf_monitor/__init__.py
tty_egpf_monitor/cli.py
tty_egpf_monitor/client.py
tty_egpf_monitor/models.py
tty_egpf_monitor/py.typed
tty_egpf_monitor-0.7.33.dist-info/METADATA
tty_egpf_monitor-0.7.33.dist-info/WHEEL
tty_egpf_monitor-0.7.33.dist-info/entry_points.txt
tty_egpf_monitor-0.7.33.dist-info/top_level.txt
tty_egpf_monitor-0.7.33.dist-info/RECORD
