Metadata-Version: 2.4
Name: tty-egpf-monitor
Version: 0.7.33
Summary: Python client library for TTY eBPF Monitor daemon
Home-page: https://github.com/seelso-net/tty-egpf-monitor
Author: TTY eBPF Monitor Team
Author-email: TTY eBPF Monitor Team <contact@seelso.net>
Maintainer-email: TTY eBPF Monitor Team <contact@seelso.net>
License: GPL-3.0
Project-URL: Homepage, https://github.com/seelso-net/tty-egpf-monitor
Project-URL: Documentation, https://github.com/seelso-net/tty-egpf-monitor/blob/main/README.md
Project-URL: Repository, https://github.com/seelso-net/tty-egpf-monitor
Project-URL: Bug Tracker, https://github.com/seelso-net/tty-egpf-monitor/issues
Project-URL: APT Repository, https://seelso-net.github.io/tty-egpf-monitor
Keywords: serial,tty,monitoring,ebpf,uart,debugging,reverse-engineering,protocol-analysis,hardware
Classifier: Development Status :: 4 - Beta
Classifier: Environment :: Console
Classifier: Intended Audience :: Developers
Classifier: Intended Audience :: System Administrators
Classifier: License :: OSI Approved :: GNU General Public License v3 (GPLv3)
Classifier: Operating System :: POSIX :: Linux
Classifier: Programming Language :: Python :: 3
Classifier: Programming Language :: Python :: 3.8
Classifier: Programming Language :: Python :: 3.9
Classifier: Programming Language :: Python :: 3.10
Classifier: Programming Language :: Python :: 3.11
Classifier: Programming Language :: Python :: 3.12
Classifier: Topic :: Software Development :: Libraries :: Python Modules
Classifier: Topic :: System :: Hardware :: Hardware Drivers
Classifier: Topic :: System :: Monitoring
Classifier: Topic :: System :: Networking :: Monitoring
Classifier: Topic :: Terminals :: Serial
Requires-Python: >=3.8
Provides-Extra: dev
Requires-Dist: pytest>=6.0; extra == "dev"
Requires-Dist: pytest-cov; extra == "dev"
Requires-Dist: black; extra == "dev"
Requires-Dist: flake8; extra == "dev"
Requires-Dist: mypy; extra == "dev"
Requires-Dist: build; extra == "dev"
Requires-Dist: twine; extra == "dev"
Dynamic: author
Dynamic: home-page
Dynamic: requires-python
